deepseek/__init__.py
deepseek/api.py
deepseek/const.py
deepseek-0.0.1.dev3.dist-info/METADATA
deepseek-0.0.1.dev3.dist-info/WHEEL
deepseek-0.0.1.dev3.dist-info/top_level.txt
deepseek-0.0.1.dev3.dist-info/RECORD
