Metadata-Version: 2.1
Name: deepseek
Version: 0.0.1.dev3
Summary: Deepseek API Library
Home-page: https://github.com/deskpai/deepseek
Author: Deskpai.com
Author-email: dev@deskpai.com
License: Apache-2.0
Keywords: deepseek
Classifier: Programming Language :: Python :: 3
Classifier: Programming Language :: Python :: 3.8
Classifier: Programming Language :: Python :: 3.9
Classifier: Programming Language :: Python :: 3.10
Classifier: Programming Language :: Python :: 3.11
Classifier: Programming Language :: Python :: 3.12
Classifier: Programming Language :: Python :: 3.13
Classifier: Programming Language :: Python :: 3.14
Requires-Dist: requests
